pyiaacsync/__init__.py
pyiaacsync/pyiaacsync.py
pyiaacsync-0.8.dist-info/LICENSE
pyiaacsync-0.8.dist-info/METADATA
pyiaacsync-0.8.dist-info/WHEEL
pyiaacsync-0.8.dist-info/top_level.txt
pyiaacsync-0.8.dist-info/RECORD
