Metadata-Version: 2.1
Name: pyiaacsync
Version: 0.8
Summary: Deploy infrastructure as code via polling
Home-page: https://github.com/manasmbellani/pyiaacsync
License-File: LICENSE
Requires-Dist: pyyaml
